jraft.abi3.so
jraft.abi3.h
jina-3.34.0.dist-info/RECORD
jina-3.34.0.dist-info/WHEEL
jina-3.34.0.dist-info/entry_points.txt
jina-3.34.0.dist-info/top_level.txt
jina-3.34.0.dist-info/METADATA
jina-3.34.0.dist-info/licenses/LICENSE
jina_cli/lookup.py
jina_cli/__init__.py
jina_cli/export.py
jina_cli/api.py
jina_cli/autocomplete.py
jina_cli/known_plugins.py
tests/conftest.py
tests/__init__.py
tests/helper.py
tests/unit/test_progress_bar.py
tests/unit/test_helper.py
tests/unit/test_gateway.py
tests/unit/test_importer.py
tests/unit/__init__.py
tests/unit/test_yamlparser.py
tests/unit/test_cli.py
tests/unit/test_extend_fastapi.py
tests/unit/clients/test_client_grpc_channel_options.py
tests/unit/clients/test_helper.py
tests/unit/clients/__init__.py
tests/unit/clients/test_asyncio.py
tests/unit/clients/test_log_config.py
tests/unit/clients/test_interface.py
tests/unit/clients/python/test_request.py
tests/unit/clients/python/test_client_errors.py
tests/unit/clients/python/__init__.py
tests/unit/clients/python/test_on_err.py
tests/unit/clients/python/test_client.py
tests/unit/parsers/test_warnings.py
tests/unit/parsers/__init__.py
tests/unit/parsers/peapods/__init__.py
tests/unit/parsers/peapods/runtimes/test_port_protocol_parser.py
tests/unit/parsers/peapods/runtimes/test_remote_parser.py
tests/unit/parsers/peapods/runtimes/__init__.py
tests/unit/parsers/peapods/runtimes/test_runtime_parser.py
tests/unit/types/__init__.py
tests/unit/types/request/test_request.py
tests/unit/types/request/__init__.py
tests/unit/types/request/test_status_message.py
tests/unit/exceptions/test_exceptions.py
tests/unit/exceptions/__init__.py
tests/unit/schemas/__init__.py
tests/unit/schemas/test_schema.py
tests/unit/jaml/__init__.py
tests/unit/jaml/test_gateway_parse.py
tests/unit/jaml/test_type_parse.py
tests/unit/jaml/parsers/__init__.py
tests/unit/jaml/parsers/executors/__init__.py
tests/unit/jaml/parsers/executors/test_legacy.py
tests/unit/serve/__init__.py
tests/unit/serve/dynamic_batching/__init__.py
tests/unit/serve/dynamic_batching/test_batch_queue.py
tests/unit/serve/networking/conftest.py
tests/unit/serve/networking/__init__.py
