Metadata-Version: 2.4
Name: jina
Version: 3.34.0
Summary: Multimodal AI services & pipelines with cloud-native stack: gRPC, Kubernetes, Docker, OpenTelemetry, Prometheus, Jaeger, etc.
Home-page: https://github.com/jina-ai/jina/
Download-URL: https://github.com/jina-ai/jina/tags
Author: Jina AI
Author-email: hello@jina.ai
License: Apache 2.0
Project-URL: Documentation, https://jina.ai/serve
Project-URL: Source, https://github.com/jina-ai/jina/
Project-URL: Tracker, https://github.com/jina-ai/jina/issues
Keywords: jina cloud-native cross-modal multimodal neural-search query search index elastic neural-network encoding embedding serving docker container image video audio deep-learning mlops
Classifier: Development Status :: 5 - Production/Stable
Classifier: Intended Audience :: Developers
Classifier: Intended Audience :: Education
Classifier: Intended Audience :: Science/Research
Classifier: Programming Language :: Python :: 3.7
Classifier: Programming Language :: Python :: 3.8
Classifier: Programming Language :: Python :: 3.9
Classifier: Programming Language :: Python :: 3.10
Classifier: Programming Language :: Python :: 3.11
Classifier: Programming Language :: Unix Shell
Classifier: Environment :: Console
Classifier: License :: OSI Approved :: Apache Software License
Classifier: Operating System :: OS Independent
Classifier: Topic :: Database :: Database Engines/Servers
Classifier: Topic :: Scientific/Engineering :: Artificial Intelligence
Classifier: Topic :: Internet :: WWW/HTTP :: Indexing/Search
Classifier: Topic :: Scientific/Engineering :: Image Recognition
Classifier: Topic :: Multimedia :: Video
Classifier: Topic :: Scientific/Engineering
Classifier: Topic :: Scientific/Engineering :: Mathematics
Classifier: Topic :: Software Development
Classifier: Topic :: Software Development :: Libraries
Classifier: Topic :: Software Development :: Libraries :: Python Modules
License-File: LICENSE
Requires-Dist: opentelemetry-sdk>=1.14.0
Requires-Dist: packaging>=20.0
Requires-Dist: jcloud>=0.0.35
Requires-Dist: grpcio-health-checking<=1.68.0,>=1.46.0
Requires-Dist: aiofiles
Requires-Dist: jina-hubble-sdk>=0.30.4
Requires-Dist: numpy
Requires-Dist: fastapi>=0.76.0
Requires-Dist: docarray>=0.16.4
Requires-Dist: opentelemetry-instrumentation-aiohttp-client>=0.33b0
Requires-Dist: opentelemetry-exporter-prometheus>=0.33b0
Requires-Dist: filelock
Requires-Dist: websockets
Requires-Dist: pathspec
Requires-Dist: aiohttp
Requires-Dist: opentelemetry-exporter-otlp>=1.12.0
Requires-Dist: docker
Requires-Dist: opentelemetry-instrumentation-grpc>=0.35b0
Requires-Dist: pydantic<3.0.0
Requires-Dist: grpcio-reflection<=1.68.0,>=1.46.0
Requires-Dist: grpcio<=1.68.0,>=1.46.0
Requires-Dist: uvicorn<=0.23.1
Requires-Dist: prometheus_client>=0.12.0
Requires-Dist: opentelemetry-api>=1.12.0
Requires-Dist: protobuf>=3.19.0
Requires-Dist: pyyaml>=5.3.1
Requires-Dist: uvloop; platform_system != "Windows"
Requires-Dist: requests
Requires-Dist: opentelemetry-exporter-otlp-proto-grpc>=1.13.0
Requires-Dist: python-multipart
Requires-Dist: urllib3<2.0.0,>=1.25.9
Requires-Dist: opentelemetry-instrumentation-fastapi>=0.33b0
Provides-Extra: core
Requires-Dist: docarray>=0.16.4; extra == "core"
Requires-Dist: packaging>=20.0; extra == "core"
Requires-Dist: jcloud>=0.0.35; extra == "core"
Requires-Dist: grpcio-health-checking<=1.68.0,>=1.46.0; extra == "core"
Requires-Dist: urllib3<2.0.0,>=1.25.9; extra == "core"
Requires-Dist: opentelemetry-instrumentation-grpc>=0.35b0; extra == "core"
Requires-Dist: pydantic<3.0.0; extra == "core"
Requires-Dist: jina-hubble-sdk>=0.30.4; extra == "core"
Requires-Dist: grpcio-reflection<=1.68.0,>=1.46.0; extra == "core"
Requires-Dist: numpy; extra == "core"
Requires-Dist: grpcio<=1.68.0,>=1.46.0; extra == "core"
Requires-Dist: opentelemetry-api>=1.12.0; extra == "core"
Requires-Dist: protobuf>=3.19.0; extra == "core"
Requires-Dist: pyyaml>=5.3.1; extra == "core"
Provides-Extra: numpy
Requires-Dist: numpy; extra == "numpy"
Provides-Extra: protobuf
Requires-Dist: protobuf>=3.19.0; extra == "protobuf"
Provides-Extra: grpcio
Requires-Dist: grpcio<=1.68.0,>=1.46.0; extra == "grpcio"
Provides-Extra: grpcio-reflection
Requires-Dist: grpcio-reflection<=1.68.0,>=1.46.0; extra == "grpcio-reflection"
Provides-Extra: grpcio-health-checking
Requires-Dist: grpcio-health-checking<=1.68.0,>=1.46.0; extra == "grpcio-health-checking"
Provides-Extra: pyyaml
Requires-Dist: pyyaml>=5.3.1; extra == "pyyaml"
Provides-Extra: packaging
Requires-Dist: packaging>=20.0; extra == "packaging"
Provides-Extra: docarray
Requires-Dist: docarray>=0.16.4; extra == "docarray"
Provides-Extra: jina-hubble-sdk
Requires-Dist: jina-hubble-sdk>=0.30.4; extra == "jina-hubble-sdk"
Provides-Extra: jcloud
Requires-Dist: jcloud>=0.0.35; extra == "jcloud"
Provides-Extra: opentelemetry-api
Requires-Dist: opentelemetry-api>=1.12.0; extra == "opentelemetry-api"
Provides-Extra: opentelemetry-instrumentation-grpc
Requires-Dist: opentelemetry-instrumentation-grpc>=0.35b0; extra == "opentelemetry-instrumentation-grpc"
Provides-Extra: uvloop
Requires-Dist: uvloop; extra == "uvloop"
Provides-Extra: perf
Requires-Dist: uvloop; extra == "perf"
Requires-Dist: opentelemetry-sdk>=1.14.0; extra == "perf"
Requires-Dist: opentelemetry-exporter-prometheus>=0.33b0; extra == "perf"
Requires-Dist: opentelemetry-instrumentation-aiohttp-client>=0.33b0; extra == "perf"
Requires-Dist: opentelemetry-exporter-otlp-proto-grpc>=1.13.0; extra == "perf"
Requires-Dist: opentelemetry-exporter-otlp>=1.12.0; extra == "perf"
Requires-Dist: prometheus_client>=0.12.0; extra == "perf"
Requires-Dist: opentelemetry-instrumentation-fastapi>=0.33b0; extra == "perf"
Provides-Extra: standard
Requires-Dist: uvloop; extra == "standard"
Requires-Dist: opentelemetry-sdk>=1.14.0; extra == "standard"
Requires-Dist: opentelemetry-exporter-prometheus>=0.33b0; extra == "standard"
Requires-Dist: opentelemetry-instrumentation-aiohttp-client>=0.33b0; extra == "standard"
Requires-Dist: uvicorn<=0.23.1; extra == "standard"
Requires-Dist: docker; extra == "standard"
Requires-Dist: filelock; extra == "standard"
Requires-Dist: requests; extra == "standard"
Requires-Dist: websockets; extra == "standard"
Requires-Dist: aiofiles; extra == "standard"
Requires-Dist: pathspec; extra == "standard"
Requires-Dist: aiohttp; extra == "standard"
Requires-Dist: python-multipart; extra == "standard"
Requires-Dist: opentelemetry-exporter-otlp>=1.12.0; extra == "standard"
Requires-Dist: fastapi>=0.76.0; extra == "standard"
Requires-Dist: prometheus_client>=0.12.0; extra == "standard"
Requires-Dist: opentelemetry-instrumentation-fastapi>=0.33b0; extra == "standard"
Provides-Extra: devel
Requires-Dist: opentelemetry-sdk>=1.14.0; extra == "devel"
Requires-Dist: strawberry-graphql>=0.96.0; extra == "devel"
Requires-Dist: aiofiles; extra == "devel"
Requires-Dist: fastapi>=0.76.0; extra == "devel"
Requires-Dist: opentelemetry-instrumentation-aiohttp-client>=0.33b0; extra == "devel"
Requires-Dist: opentelemetry-exporter-prometheus>=0.33b0; extra == "devel"
Requires-Dist: filelock; extra == "devel"
Requires-Dist: websockets; extra == "devel"
Requires-Dist: pathspec; extra == "devel"
Requires-Dist: aiohttp; extra == "devel"
Requires-Dist: watchfiles>=0.18.0; extra == "devel"
Requires-Dist: opentelemetry-exporter-otlp>=1.12.0; extra == "devel"
Requires-Dist: sgqlc; extra == "devel"
Requires-Dist: docker; extra == "devel"
Requires-Dist: uvicorn<=0.23.1; extra == "devel"
Requires-Dist: prometheus_client>=0.12.0; extra == "devel"
Requires-Dist: uvloop; platform_system != "Windows" and extra == "devel"
Requires-Dist: requests; extra == "devel"
Requires-Dist: opentelemetry-exporter-otlp-proto-grpc>=1.13.0; extra == "devel"
Requires-Dist: python-multipart; extra == "devel"
Requires-Dist: opentelemetry-instrumentation-fastapi>=0.33b0; extra == "devel"
Provides-Extra: prometheus-client
Requires-Dist: prometheus_client>=0.12.0; extra == "prometheus-client"
Provides-Extra: opentelemetry-sdk
Requires-Dist: opentelemetry-sdk>=1.14.0; extra == "opentelemetry-sdk"
Provides-Extra: opentelemetry-exporter-otlp
Requires-Dist: opentelemetry-exporter-otlp>=1.12.0; extra == "opentelemetry-exporter-otlp"
Provides-Extra: opentelemetry-exporter-prometheus
Requires-Dist: opentelemetry-exporter-prometheus>=0.33b0; extra == "opentelemetry-exporter-prometheus"
Provides-Extra: opentelemetry-instrumentation-aiohttp-client
Requires-Dist: opentelemetry-instrumentation-aiohttp-client>=0.33b0; extra == "opentelemetry-instrumentation-aiohttp-client"
Provides-Extra: opentelemetry-instrumentation-fastapi
Requires-Dist: opentelemetry-instrumentation-fastapi>=0.33b0; extra == "opentelemetry-instrumentation-fastapi"
Provides-Extra: standrad
Requires-Dist: opentelemetry-exporter-otlp-proto-grpc>=1.13.0; extra == "standrad"
Provides-Extra: opentelemetry-exporter-otlp-proto-grpc
Requires-Dist: opentelemetry-exporter-otlp-proto-grpc>=1.13.0; extra == "opentelemetry-exporter-otlp-proto-grpc"
Provides-Extra: fastapi
Requires-Dist: fastapi>=0.76.0; extra == "fastapi"
Provides-Extra: uvicorn
Requires-Dist: uvicorn<=0.23.1; extra == "uvicorn"
Provides-Extra: docker
Requires-Dist: docker; extra == "docker"
Provides-Extra: pathspec
Requires-Dist: pathspec; extra == "pathspec"
Provides-Extra: filelock
Requires-Dist: filelock; extra == "filelock"
Provides-Extra: requests
Requires-Dist: requests; extra == "requests"
Provides-Extra: websockets
Requires-Dist: websockets; extra == "websockets"
Provides-Extra: pydantic
Requires-Dist: pydantic<3.0.0; extra == "pydantic"
Provides-Extra: python-multipart
Requires-Dist: python-multipart; extra == "python-multipart"
Provides-Extra: aiofiles
Requires-Dist: aiofiles; extra == "aiofiles"
Provides-Extra: aiohttp
Requires-Dist: aiohttp; extra == "aiohttp"
Provides-Extra: scipy
Requires-Dist: scipy>=1.6.1; extra == "scipy"
Provides-Extra: test
Requires-Dist: black==24.3.0; extra == "test"
Requires-Dist: pytest-repeat; extra == "test"
Requires-Dist: Pillow; extra == "test"
Requires-Dist: mock; extra == "test"
Requires-Dist: psutil; extra == "test"
Requires-Dist: pytest-cov==3.0.0; extra == "test"
Requires-Dist: pytest-mock; extra == "test"
Requires-Dist: pytest-reraise; extra == "test"
Requires-Dist: pytest-custom_exit_code; extra == "test"
Requires-Dist: flaky; extra == "test"
Requires-Dist: kubernetes<31.0.0,>=18.20.0; extra == "test"
Requires-Dist: pytest-kind==22.11.1; extra == "test"
Requires-Dist: opentelemetry-test-utils>=0.33b0; extra == "test"
Requires-Dist: pytest-asyncio<0.23.0; extra == "test"
Requires-Dist: prometheus-api-client>=0.5.1; extra == "test"
Requires-Dist: scipy>=1.6.1; extra == "test"
Requires-Dist: requests-mock; extra == "test"
Requires-Dist: pytest-timeout; extra == "test"
Requires-Dist: coverage==6.2; extra == "test"
Requires-Dist: pytest-lazy-fixture; extra == "test"
Requires-Dist: pytest<8.0.0; extra == "test"
Provides-Extra: pillow
Requires-Dist: Pillow; extra == "pillow"
Provides-Extra: pytest
Requires-Dist: pytest<8.0.0; extra == "pytest"
Provides-Extra: pytest-timeout
Requires-Dist: pytest-timeout; extra == "pytest-timeout"
Provides-Extra: pytest-mock
Requires-Dist: pytest-mock; extra == "pytest-mock"
Provides-Extra: pytest-cov
Requires-Dist: pytest-cov==3.0.0; extra == "pytest-cov"
Provides-Extra: coverage
Requires-Dist: coverage==6.2; extra == "coverage"
Provides-Extra: pytest-repeat
Requires-Dist: pytest-repeat; extra == "pytest-repeat"
Provides-Extra: pytest-asyncio
Requires-Dist: pytest-asyncio<0.23.0; extra == "pytest-asyncio"
Provides-Extra: pytest-reraise
Requires-Dist: pytest-reraise; extra == "pytest-reraise"
Provides-Extra: flaky
Requires-Dist: flaky; extra == "flaky"
Provides-Extra: mock
Requires-Dist: mock; extra == "mock"
Provides-Extra: requests-mock
Requires-Dist: requests-mock; extra == "requests-mock"
Provides-Extra: pytest-custom-exit-code
Requires-Dist: pytest-custom_exit_code; extra == "pytest-custom-exit-code"
Provides-Extra: black
Requires-Dist: black==24.3.0; extra == "black"
Provides-Extra: kubernetes
Requires-Dist: kubernetes<31.0.0,>=18.20.0; extra == "kubernetes"
Provides-Extra: pytest-kind
Requires-Dist: pytest-kind==22.11.1; extra == "pytest-kind"
Provides-Extra: pytest-lazy-fixture
Requires-Dist: pytest-lazy-fixture; extra == "pytest-lazy-fixture"
Provides-Extra: torch
Requires-Dist: torch; extra == "torch"
Provides-Extra: cicd
Requires-Dist: torch; extra == "cicd"
Requires-Dist: strawberry-graphql>=0.96.0; extra == "cicd"
Requires-Dist: bs4; extra == "cicd"
Requires-Dist: portforward<0.4.3,>=0.2.4; extra == "cicd"
Requires-Dist: sgqlc; extra == "cicd"
Requires-Dist: tensorflow>=2.0; extra == "cicd"
Requires-Dist: jsonschema; extra == "cicd"
Provides-Extra: psutil
Requires-Dist: psutil; extra == "psutil"
Provides-Extra: strawberry-graphql
Requires-Dist: strawberry-graphql>=0.96.0; extra == "strawberry-graphql"
Provides-Extra: sgqlc
Requires-Dist: sgqlc; extra == "sgqlc"
Provides-Extra: bs4
Requires-Dist: bs4; extra == "bs4"
Provides-Extra: jsonschema
Requires-Dist: jsonschema; extra == "jsonschema"
Provides-Extra: portforward
Requires-Dist: portforward<0.4.3,>=0.2.4; extra == "portforward"
Provides-Extra: tensorflow
Requires-Dist: tensorflow>=2.0; extra == "tensorflow"
Provides-Extra: opentelemetry-test-utils
Requires-Dist: opentelemetry-test-utils>=0.33b0; extra == "opentelemetry-test-utils"
Provides-Extra: prometheus-api-client
Requires-Dist: prometheus-api-client>=0.5.1; extra == "prometheus-api-client"
Provides-Extra: watchfiles
Requires-Dist: watchfiles>=0.18.0; extra == "watchfiles"
Provides-Extra: urllib3
Requires-Dist: urllib3<2.0.0,>=1.25.9; extra == "urllib3"
Provides-Extra: all
Requires-Dist: black==24.3.0; extra == "all"
Requires-Dist: opentelemetry-sdk>=1.14.0; extra == "all"
Requires-Dist: packaging>=20.0; extra == "all"
Requires-Dist: jcloud>=0.0.35; extra == "all"
Requires-Dist: grpcio-health-checking<=1.68.0,>=1.46.0; extra == "all"
Requires-Dist: strawberry-graphql>=0.96.0; extra == "all"
Requires-Dist: aiofiles; extra == "all"
Requires-Dist: jina-hubble-sdk>=0.30.4; extra == "all"
Requires-Dist: numpy; extra == "all"
Requires-Dist: fastapi>=0.76.0; extra == "all"
Requires-Dist: pytest-repeat; extra == "all"
Requires-Dist: docarray>=0.16.4; extra == "all"
Requires-Dist: Pillow; extra == "all"
Requires-Dist: opentelemetry-instrumentation-aiohttp-client>=0.33b0; extra == "all"
Requires-Dist: opentelemetry-exporter-prometheus>=0.33b0; extra == "all"
Requires-Dist: mock; extra == "all"
Requires-Dist: filelock; extra == "all"
Requires-Dist: websockets; extra == "all"
Requires-Dist: pathspec; extra == "all"
Requires-Dist: aiohttp; extra == "all"
Requires-Dist: watchfiles>=0.18.0; extra == "all"
Requires-Dist: psutil; extra == "all"
Requires-Dist: opentelemetry-exporter-otlp>=1.12.0; extra == "all"
Requires-Dist: pytest-cov==3.0.0; extra == "all"
Requires-Dist: pytest-mock; extra == "all"
Requires-Dist: sgqlc; extra == "all"
Requires-Dist: pytest-reraise; extra == "all"
Requires-Dist: pytest-custom_exit_code; extra == "all"
Requires-Dist: flaky; extra == "all"
Requires-Dist: docker; extra == "all"
Requires-Dist: kubernetes<31.0.0,>=18.20.0; extra == "all"
Requires-Dist: pytest-kind==22.11.1; extra == "all"
Requires-Dist: opentelemetry-instrumentation-fastapi>=0.33b0; extra == "all"
Requires-Dist: opentelemetry-instrumentation-grpc>=0.35b0; extra == "all"
Requires-Dist: opentelemetry-test-utils>=0.33b0; extra == "all"
Requires-Dist: pydantic<3.0.0; extra == "all"
Requires-Dist: pytest-asyncio<0.23.0; extra == "all"
Requires-Dist: grpcio-reflection<=1.68.0,>=1.46.0; extra == "all"
Requires-Dist: prometheus-api-client>=0.5.1; extra == "all"
Requires-Dist: grpcio<=1.68.0,>=1.46.0; extra == "all"
Requires-Dist: uvicorn<=0.23.1; extra == "all"
Requires-Dist: prometheus_client>=0.12.0; extra == "all"
Requires-Dist: opentelemetry-api>=1.12.0; extra == "all"
Requires-Dist: protobuf>=3.19.0; extra == "all"
Requires-Dist: pyyaml>=5.3.1; extra == "all"
Requires-Dist: torch; extra == "all"
Requires-Dist: scipy>=1.6.1; extra == "all"
Requires-Dist: uvloop; platform_system != "Windows" and extra == "all"
Requires-Dist: requests; extra == "all"
Requires-Dist: requests-mock; extra == "all"
Requires-Dist: pytest-timeout; extra == "all"
Requires-Dist: bs4; extra == "all"
Requires-Dist: coverage==6.2; extra == "all"
Requires-Dist: opentelemetry-exporter-otlp-proto-grpc>=1.13.0; extra == "all"
Requires-Dist: portforward<0.4.3,>=0.2.4; extra == "all"
Requires-Dist: python-multipart; extra == "all"
Requires-Dist: pytest-lazy-fixture; extra == "all"
Requires-Dist: urllib3<2.0.0,>=1.25.9; extra == "all"
Requires-Dist: pytest<8.0.0; extra == "all"
Requires-Dist: tensorflow>=2.0; extra == "all"
Requires-Dist: jsonschema; extra == "all"
Dynamic: author
Dynamic: author-email
Dynamic: classifier
Dynamic: description
Dynamic: description-content-type
Dynamic: download-url
Dynamic: home-page
Dynamic: keywords
Dynamic: license
Dynamic: license-file
Dynamic: project-url
Dynamic: provides-extra
Dynamic: requires-dist
Dynamic: summary
